{
 "id": 1,
 "body": {
  "part": [
   {
    "id": "CoreComponent",
    "type": "CoreComponent",
    "root": true,
    "orientation": 0
   },
   {
    "id": "myid1002",
    "type": "PassiveHinge",
    "root": false,
    "orientation": 2
   },
   {
    "id": "myid1003",
    "type": "ActiveHinge",
    "root": false,
    "orientation": 3
   },
   {
    "id": "myid1027",
    "type": "ParametricJoint",
    "root": false,
    "evolvableParam": [
     {
      "paramValue": 0.067704237997531891
     },
     {
      "paramValue": 70.763145446777344
     },
     {
      "paramValue": 0.0
     }
    ],
    "orientation": 0
   },
   {
    "id": "myid1021",
    "type": "ParametricJoint",
    "root": false,
    "evolvableParam": [
     {
      "paramValue": 0.039129398763179779
     },
     {
      "paramValue": 8.5113582611083984
     },
     {
      "paramValue": 0.0
     }
    ],
    "orientation": 2
   },
   {
    "id": "myid1000",
    "type": "ActiveHinge",
    "root": false,
    "orientation": 3
   },
   {
    "id": "myid1005",
    "type": "FixedBrick",
    "root": false,
    "orientation": 0
   },
   {
    "id": "myid1033",
    "type": "ParametricJoint",
    "root": false,
    "evolvableParam": [
     {
      "paramValue": 0.059973530471324921
     },
     {
      "paramValue": -6.5506420135498047
     },
     {
      "paramValue": 0.0
     }
    ],
    "orientation": 0
   },
   {
    "id": "myid1042",
    "type": "IrSensor",
    "root": false,
    "orientation": 0
   },
   {
    "id": "myid1009",
    "type": "ActiveHinge",
    "root": false,
    "orientation": 3
   },
   {
    "id": "myid1010",
    "type": "FixedBrick",
    "root": false,
    "orientation": 3
   },
   {
    "id": "myid1013",
    "type": "ActiveHinge",
    "root": false,
    "orientation": 2
   },
   {
    "id": "myid1007",
    "type": "ActiveHinge",
    "root": false,
    "orientation": 3
   },
   {
    "id": "myid1032",
    "type": "PassiveHinge",
    "root": false,
    "orientation": 1
   },
   {
    "id": "myid1016",
    "type": "ActiveHinge",
    "root": false,
    "orientation": 2
   },
   {
    "id": "myid1023",
    "type": "ParametricJoint",
    "root": false,
    "evolvableParam": [
     {
      "paramValue": 0.05002959817647934
     },
     {
      "paramValue": 27.535362243652344
     },
     {
      "paramValue": 0.0
     }
    ],
    "orientation": 1
   },
   {
    "id": "myid1035",
    "type": "IrSensor",
    "root": false,
    "orientation": 0
   },
   {
    "id": "myid1034",
    "type": "ParametricJoint",
    "root": false,
    "evolvableParam": [
     {
      "paramValue": 0.053831338882446289
     },
     {
      "paramValue": -48.315818786621094
     },
     {
      "paramValue": 0.0
     }
    ],
    "orientation": 0
   },
   {
    "id": "myid1011",
    "type": "ActiveHinge",
    "root": false,
    "orientation": 3
   },
   {
    "id": "myid1024",
    "type": "ParametricJoint",
    "root": false,
    "evolvableParam": [
     {
      "paramValue": 0.05002959817647934
     },
     {
      "paramValue": 27.535362243652344
     },
     {
      "paramValue": 0.0
     }
    ],
    "orientation": 1
   }
  ],
  "connection": [
   {
    "src": "CoreComponent",
    "dest": "myid1002",
    "srcSlot": 0,
    "destSlot": 0
   },
   {
    "src": "myid1002",
    "dest": "myid1003",
    "srcSlot": 1,
    "destSlot": 0
   },
   {
    "src": "myid1003",
    "dest": "myid1027",
    "srcSlot": 1,
    "destSlot": 0
   },
   {
    "src": "myid1027",
    "dest": "myid1021",
    "srcSlot": 1,
    "destSlot": 0
   },
   {
    "src": "myid1021",
    "dest": "myid1000",
    "srcSlot": 1,
    "destSlot": 0
   },
   {
    "src": "myid1000",
    "dest": "myid1005",
    "srcSlot": 1,
    "destSlot": 0
   },
   {
    "src": "myid1005",
    "dest": "myid1033",
    "srcSlot": 1,
    "destSlot": 0
   },
   {
    "src": "myid1005",
    "dest": "myid1042",
    "srcSlot": 2,
    "destSlot": 0
   },
   {
    "src": "myid1005",
    "dest": "myid1009",
    "srcSlot": 3,
    "destSlot": 0
   },
   {
    "src": "myid1009",
    "dest": "myid1010",
    "srcSlot": 1,
    "destSlot": 0
   },
   {
    "src": "myid1010",
    "dest": "myid1013",
    "srcSlot": 1,
    "destSlot": 0
   },
   {
    "src": "myid1013",
    "dest": "myid1007",
    "srcSlot": 1,
    "destSlot": 0
   },
   {
    "src": "myid1007",
    "dest": "myid1032",
    "srcSlot": 1,
    "destSlot": 0
   },
   {
    "src": "myid1032",
    "dest": "myid1016",
    "srcSlot": 1,
    "destSlot": 0
   },
   {
    "src": "myid1016",
    "dest": "myid1023",
    "srcSlot": 1,
    "destSlot": 0
   },
   {
    "src": "myid1023",
    "dest": "myid1035",
    "srcSlot": 1,
    "destSlot": 0
   },
   {
    "src": "myid1010",
    "dest": "myid1034",
    "srcSlot": 2,
    "destSlot": 0
   },
   {
    "src": "myid1010",
    "dest": "myid1011",
    "srcSlot": 3,
    "destSlot": 0
   },
   {
    "src": "myid1011",
    "dest": "myid1024",
    "srcSlot": 1,
    "destSlot": 0
   }
  ]
 },
 "brain": {
  "neuron": [
   {
    "id": "CoreComponent-0",
    "layer": "input",
    "type": "simple",
    "bodyPartId": "CoreComponent",
    "ioId": 0,
    "gain": 1.0
   },
   {
    "id": "CoreComponent-1",
    "layer": "input",
    "type": "simple",
    "bodyPartId": "CoreComponent",
    "ioId": 1,
    "gain": 1.0
   },
   {
    "id": "CoreComponent-2",
    "layer": "input",
    "type": "simple",
    "bodyPartId": "CoreComponent",
    "ioId": 2,
    "gain": 1.0
   },
   {
    "id": "CoreComponent-3",
    "layer": "input",
    "type": "simple",
    "bodyPartId": "CoreComponent",
    "ioId": 3,
    "gain": 1.0
   },
   {
    "id": "CoreComponent-4",
    "layer": "input",
    "type": "simple",
    "bodyPartId": "CoreComponent",
    "ioId": 4,
    "gain": 1.0
   },
   {
    "id": "CoreComponent-5",
    "layer": "input",
    "type": "simple",
    "bodyPartId": "CoreComponent",
    "ioId": 5,
    "gain": 1.0
   },
   {
    "id": "myid1000-0",
    "layer": "output",
    "type": "sigmoid",
    "bias": 1.7114022970199585,
    "bodyPartId": "myid1000",
    "ioId": 0,
    "gain": 1.0
   },
   {
    "id": "myid1003-0",
    "layer": "output",
    "type": "sigmoid",
    "bias": -2.7797825336456299,
    "bodyPartId": "myid1003",
    "ioId": 0,
    "gain": 1.0
   },
   {
    "id": "myid1007-0",
    "layer": "output",
    "type": "sigmoid",
    "bias": -3.7094628810882568,
    "bodyPartId": "myid1007",
    "ioId": 0,
    "gain": 1.0
   },
   {
    "id": "myid1009-0",
    "layer": "output",
    "type": "sigmoid",
    "bias": 3.317734956741333,
    "bodyPartId": "myid1009",
    "ioId": 0,
    "gain": 1.0
   },
   {
    "id": "myid1011-0",
    "layer": "output",
    "type": "sigmoid",
    "bias": -0.13663399219512939,
    "bodyPartId": "myid1011",
    "ioId": 0,
    "gain": 1.0
   },
   {
    "id": "myid1013-0",
    "layer": "output",
    "type": "sigmoid",
    "bias": 3.1108207702636719,
    "bodyPartId": "myid1013",
    "ioId": 0,
    "gain": 1.0
   },
   {
    "id": "myid1016-0",
    "layer": "output",
    "type": "sigmoid",
    "bias": -0.53871113061904907,
    "bodyPartId": "myid1016",
    "ioId": 0,
    "gain": 1.0
   },
   {
    "id": "myid1035-0",
    "layer": "input",
    "type": "simple",
    "bodyPartId": "myid1035",
    "ioId": 0,
    "gain": 1.0
   },
   {
    "id": "myid1042-0",
    "layer": "input",
    "type": "simple",
    "bodyPartId": "myid1042",
    "ioId": 0,
    "gain": 1.0
   }
  ],
  "connection": [
   {
    "src": "CoreComponent-0",
    "dest": "myid1000-0",
    "weight": -2.3261849880218506
   },
   {
    "src": "CoreComponent-0",
    "dest": "myid1003-0",
    "weight": -1.8826421499252319
   },
   {
    "src": "CoreComponent-0",
    "dest": "myid1007-0",
    "weight": 1.8608541488647461
   },
   {
    "src": "CoreComponent-0",
    "dest": "myid1009-0",
    "weight": 1.1098263263702393
   },
   {
    "src": "CoreComponent-0",
    "dest": "myid1011-0",
    "weight": -3.1887636184692383
   },
   {
    "src": "CoreComponent-0",
    "dest": "myid1013-0",
    "weight": 2.7560341358184814
   },
   {
    "src": "CoreComponent-0",
    "dest": "myid1016-0",
    "weight": 2.6374697685241699
   },
   {
    "src": "CoreComponent-1",
    "dest": "myid1000-0",
    "weight": -0.12266977876424789
   },
   {
    "src": "CoreComponent-1",
    "dest": "myid1003-0",
    "weight": 3.4265751838684082
   },
   {
    "src": "CoreComponent-1",
    "dest": "myid1007-0",
    "weight": 0.16961413621902466
   },
   {
    "src": "CoreComponent-1",
    "dest": "myid1009-0",
    "weight": -2.8848245143890381
   },
   {
    "src": "CoreComponent-1",
    "dest": "myid1011-0",
    "weight": -1.9539190530776978
   },
   {
    "src": "CoreComponent-1",
    "dest": "myid1013-0",
    "weight": -3.6581003665924072
   },
   {
    "src": "CoreComponent-1",
    "dest": "myid1016-0",
    "weight": 3.2463841438293457
   },
   {
    "src": "CoreComponent-2",
    "dest": "myid1000-0",
    "weight": -1.9925086498260498
   },
   {
    "src": "CoreComponent-2",
    "dest": "myid1003-0",
    "weight": 3.6792480945587158
   },
   {
    "src": "CoreComponent-2",
    "dest": "myid1007-0",
    "weight": 2.5011107921600342
   },
   {
    "src": "CoreComponent-2",
    "dest": "myid1009-0",
    "weight": 0.21239995956420898
   },
   {
    "src": "CoreComponent-2",
    "dest": "myid1011-0",
    "weight": 0.14031548798084259
   },
   {
    "src": "CoreComponent-2",
    "dest": "myid1013-0",
    "weight": 0.75590312480926514
   },
   {
    "src": "CoreComponent-2",
    "dest": "myid1016-0",
    "weight": 3.2355666160583496
   },
   {
    "src": "CoreComponent-3",
    "dest": "myid1000-0",
    "weight": 1.6764885187149048
   },
   {
    "src": "CoreComponent-3",
    "dest": "myid1003-0",
    "weight": 1.6266745328903198
   },
   {
    "src": "CoreComponent-3",
    "dest": "myid1007-0",
    "weight": 0.99177724123001099
   },
   {
    "src": "CoreComponent-3",
    "dest": "myid1009-0",
    "weight": -2.905210018157959
   },
   {
    "src": "CoreComponent-3",
    "dest": "myid1011-0",
    "weight": 0.11908175051212311
   },
   {
    "src": "CoreComponent-3",
    "dest": "myid1013-0",
    "weight": -3.4396295547485352
   },
   {
    "src": "CoreComponent-3",
    "dest": "myid1016-0",
    "weight": -3.111983060836792
   },
   {
    "src": "CoreComponent-4",
    "dest": "myid1000-0",
    "weight": -3.2743453979492187
   },
   {
    "src": "CoreComponent-4",
    "dest": "myid1003-0",
    "weight": 0.53654193878173828
   },
   {
    "src": "CoreComponent-4",
    "dest": "myid1007-0",
    "weight": -3.3640758991241455
   },
   {
    "src": "CoreComponent-4",
    "dest": "myid1009-0",
    "weight": -1.7387475967407227
   },
   {
    "src": "CoreComponent-4",
    "dest": "myid1011-0",
    "weight": -3.4864873886108398
   },
   {
    "src": "CoreComponent-4",
    "dest": "myid1013-0",
    "weight": -3.7069797515869141
   },
   {
    "src": "CoreComponent-4",
    "dest": "myid1016-0",
    "weight": 2.5935049057006836
   },
   {
    "src": "CoreComponent-5",
    "dest": "myid1000-0",
    "weight": 2.8794515132904053
   },
   {
    "src": "CoreComponent-5",
    "dest": "myid1003-0",
    "weight": -3.3991410732269287
   },
   {
    "src": "CoreComponent-5",
    "dest": "myid1007-0",
    "weight": 3.222259521484375
   },
   {
    "src": "CoreComponent-5",
    "dest": "myid1009-0",
    "weight": 1.8689737319946289
   },
   {
    "src": "CoreComponent-5",
    "dest": "myid1011-0",
    "weight": -0.70722973346710205
   },
   {
    "src": "CoreComponent-5",
    "dest": "myid1013-0",
    "weight": -3.3060784339904785
   },
   {
    "src": "CoreComponent-5",
    "dest": "myid1016-0",
    "weight": -2.4329843521118164
   },
   {
    "src": "myid1000-0",
    "dest": "myid1000-0",
    "weight": -1.8137032985687256
   },
   {
    "src": "myid1000-0",
    "dest": "myid1003-0",
    "weight": -0.98872363567352295
   },
   {
    "src": "myid1000-0",
    "dest": "myid1007-0",
    "weight": -2.2615675926208496
   },
   {
    "src": "myid1000-0",
    "dest": "myid1009-0",
    "weight": -0.41284865140914917
   },
   {
    "src": "myid1000-0",
    "dest": "myid1011-0",
    "weight": 0.44667202234268188
   },
   {
    "src": "myid1000-0",
    "dest": "myid1013-0",
    "weight": 2.6483187675476074
   },
   {
    "src": "myid1000-0",
    "dest": "myid1016-0",
    "weight": -3.1475071907043457
   },
   {
    "src": "myid1003-0",
    "dest": "myid1000-0",
    "weight": -0.6452210545539856
   },
   {
    "src": "myid1003-0",
    "dest": "myid1003-0",
    "weight": -0.25612437725067139
   },
   {
    "src": "myid1003-0",
    "dest": "myid1007-0",
    "weight": 2.7459397315979004
   },
   {
    "src": "myid1003-0",
    "dest": "myid1009-0",
    "weight": 2.2540214061737061
   },
   {
    "src": "myid1003-0",
    "dest": "myid1011-0",
    "weight": 3.3400828838348389
   },
   {
    "src": "myid1003-0",
    "dest": "myid1013-0",
    "weight": -1.3009507656097412
   },
   {
    "src": "myid1003-0",
    "dest": "myid1016-0",
    "weight": 0.56070417165756226
   },
   {
    "src": "myid1007-0",
    "dest": "myid1000-0",
    "weight": -1.0740362405776978
   },
   {
    "src": "myid1007-0",
    "dest": "myid1003-0",
    "weight": -2.5588717460632324
   },
   {
    "src": "myid1007-0",
    "dest": "myid1007-0",
    "weight": 1.0512088537216187
   },
   {
    "src": "myid1007-0",
    "dest": "myid1009-0",
    "weight": -2.8185627460479736
   },
   {
    "src": "myid1007-0",
    "dest": "myid1011-0",
    "weight": 3.6058864593505859
   },
   {
    "src": "myid1007-0",
    "dest": "myid1013-0",
    "weight": -3.8242459297180176
   },
   {
    "src": "myid1007-0",
    "dest": "myid1016-0",
    "weight": -3.9334425926208496
   },
   {
    "src": "myid1009-0",
    "dest": "myid1000-0",
    "weight": 0.65732204914093018
   },
   {
    "src": "myid1009-0",
    "dest": "myid1003-0",
    "weight": -2.4687323570251465
   },
   {
    "src": "myid1009-0",
    "dest": "myid1007-0",
    "weight": 1.1333508491516113
   },
   {
    "src": "myid1009-0",
    "dest": "myid1009-0",
    "weight": -2.9254395961761475
   },
   {
    "src": "myid1009-0",
    "dest": "myid1011-0",
    "weight": -2.1326892375946045
   },
   {
    "src": "myid1009-0",
    "dest": "myid1013-0",
    "weight": 1.1166795492172241
   },
   {
    "src": "myid1009-0",
    "dest": "myid1016-0",
    "weight": 3.7153425216674805
   },
   {
    "src": "myid1011-0",
    "dest": "myid1000-0",
    "weight": -1.8973164558410645
   },
   {
    "src": "myid1011-0",
    "dest": "myid1003-0",
    "weight": -3.8204660415649414
   },
   {
    "src": "myid1011-0",
    "dest": "myid1007-0",
    "weight": -2.7322707176208496
   },
   {
    "src": "myid1011-0",
    "dest": "myid1009-0",
    "weight": -1.4627894163131714
   },
   {
    "src": "myid1011-0",
    "dest": "myid1011-0",
    "weight": 3.9654884338378906
   },
   {
    "src": "myid1011-0",
    "dest": "myid1013-0",
    "weight": -0.99897146224975586
   },
   {
    "src": "myid1011-0",
    "dest": "myid1016-0",
    "weight": 0.44507777690887451
   },
   {
    "src": "myid1013-0",
    "dest": "myid1000-0",
    "weight": 3.24770188331604
   },
   {
    "src": "myid1013-0",
    "dest": "myid1003-0",
    "weight": -3.7627992630004883
   },
   {
    "src": "myid1013-0",
    "dest": "myid1007-0",
    "weight": 0.49170732498168945
   },
   {
    "src": "myid1013-0",
    "dest": "myid1009-0",
    "weight": -3.3501813411712646
   },
   {
    "src": "myid1013-0",
    "dest": "myid1011-0",
    "weight": -2.9086971282958984
   },
   {
    "src": "myid1013-0",
    "dest": "myid1013-0",
    "weight": -2.7139320373535156
   },
   {
    "src": "myid1013-0",
    "dest": "myid1016-0",
    "weight": 2.4736521244049072
   },
   {
    "src": "myid1016-0",
    "dest": "myid1000-0",
    "weight": 3.0967974662780762
   },
   {
    "src": "myid1016-0",
    "dest": "myid1003-0",
    "weight": -1.0409340858459473
   },
   {
    "src": "myid1016-0",
    "dest": "myid1007-0",
    "weight": -2.2691147327423096
   },
   {
    "src": "myid1016-0",
    "dest": "myid1009-0",
    "weight": -3.49068284034729
   },
   {
    "src": "myid1016-0",
    "dest": "myid1011-0",
    "weight": 3.5686583518981934
   },
   {
    "src": "myid1016-0",
    "dest": "myid1013-0",
    "weight": -0.41335278749465942
   },
   {
    "src": "myid1016-0",
    "dest": "myid1016-0",
    "weight": 1.0892033576965332
   },
   {
    "src": "myid1035-0",
    "dest": "myid1000-0",
    "weight": 1.4918842315673828
   },
   {
    "src": "myid1035-0",
    "dest": "myid1003-0",
    "weight": -0.52339977025985718
   },
   {
    "src": "myid1035-0",
    "dest": "myid1007-0",
    "weight": -1.9883228540420532
   },
   {
    "src": "myid1035-0",
    "dest": "myid1009-0",
    "weight": -3.1010024547576904
   },
   {
    "src": "myid1035-0",
    "dest": "myid1011-0",
    "weight": -0.88967388868331909
   },
   {
    "src": "myid1035-0",
    "dest": "myid1013-0",
    "weight": 2.0056824684143066
   },
   {
    "src": "myid1035-0",
    "dest": "myid1016-0",
    "weight": -1.8562061786651611
   },
   {
    "src": "myid1042-0",
    "dest": "myid1000-0",
    "weight": 3.2976744174957275
   },
   {
    "src": "myid1042-0",
    "dest": "myid1003-0",
    "weight": -3.8216552734375
   },
   {
    "src": "myid1042-0",
    "dest": "myid1007-0",
    "weight": -1.2256968021392822
   },
   {
    "src": "myid1042-0",
    "dest": "myid1009-0",
    "weight": 0.68829530477523804
   },
   {
    "src": "myid1042-0",
    "dest": "myid1011-0",
    "weight": 0.48473191261291504
   },
   {
    "src": "myid1042-0",
    "dest": "myid1013-0",
    "weight": 0.42199477553367615
   },
   {
    "src": "myid1042-0",
    "dest": "myid1016-0",
    "weight": 1.3384088277816772
   }
  ]
 }
}